noway/__init__.py
noway/noway.py
noway-0.1.dist-info/DESCRIPTION.rst
noway-0.1.dist-info/METADATA
noway-0.1.dist-info/RECORD
noway-0.1.dist-info/WHEEL
noway-0.1.dist-info/metadata.json
noway-0.1.dist-info/top_level.txt
