Metadata-Version: 2.0
Name: noway
Version: 0.1
Summary: Python interface to use the NoWay path planning application through redis.
Home-page: http://github.com/rustyducks/noway-python
Author: GuilhemBn@TheRustyDucks
Author-email: buisanguilhem@gmail.com
License: LGPLv3
Platform: UNKNOWN
Requires-Dist: redis
